google/cloud/redis/__init__.py
google/cloud/redis/gapic_version.py
google/cloud/redis/py.typed
google/cloud/redis_v1/__init__.py
google/cloud/redis_v1/gapic_metadata.json
google/cloud/redis_v1/gapic_version.py
google/cloud/redis_v1/py.typed
google/cloud/redis_v1/services/__init__.py
google/cloud/redis_v1/services/cloud_redis/__init__.py
google/cloud/redis_v1/services/cloud_redis/async_client.py
google/cloud/redis_v1/services/cloud_redis/client.py
google/cloud/redis_v1/services/cloud_redis/pagers.py
google/cloud/redis_v1/services/cloud_redis/transports/__init__.py
google/cloud/redis_v1/services/cloud_redis/transports/base.py
google/cloud/redis_v1/services/cloud_redis/transports/grpc.py
google/cloud/redis_v1/services/cloud_redis/transports/grpc_asyncio.py
google/cloud/redis_v1/services/cloud_redis/transports/rest.py
google/cloud/redis_v1/services/cloud_redis/transports/rest_base.py
google/cloud/redis_v1/types/__init__.py
google/cloud/redis_v1/types/cloud_redis.py
google/cloud/redis_v1beta1/__init__.py
google/cloud/redis_v1beta1/gapic_metadata.json
google/cloud/redis_v1beta1/gapic_version.py
google/cloud/redis_v1beta1/py.typed
google/cloud/redis_v1beta1/services/__init__.py
google/cloud/redis_v1beta1/services/cloud_redis/__init__.py
google/cloud/redis_v1beta1/services/cloud_redis/async_client.py
google/cloud/redis_v1beta1/services/cloud_redis/client.py
google/cloud/redis_v1beta1/services/cloud_redis/pagers.py
google/cloud/redis_v1beta1/services/cloud_redis/transports/__init__.py
google/cloud/redis_v1beta1/services/cloud_redis/transports/base.py
google/cloud/redis_v1beta1/services/cloud_redis/transports/grpc.py
google/cloud/redis_v1beta1/services/cloud_redis/transports/grpc_asyncio.py
google/cloud/redis_v1beta1/services/cloud_redis/transports/rest.py
google/cloud/redis_v1beta1/services/cloud_redis/transports/rest_base.py
google/cloud/redis_v1beta1/types/__init__.py
google/cloud/redis_v1beta1/types/cloud_redis.py
google_cloud_redis-2.18.1.dist-info/LICENSE
google_cloud_redis-2.18.1.dist-info/METADATA
google_cloud_redis-2.18.1.dist-info/WHEEL
google_cloud_redis-2.18.1.dist-info/top_level.txt
google_cloud_redis-2.18.1.dist-info/RECORD
